{
    "config": {
        "api_key": "adsfdsfasdf",
        "session_timeout": 30,
        "disable_location": false,
        "trigger_interval_seconds": 100
    },
    "mappings": {
        "customer_id": "user_id",
        "customer_first_name": "first_name",
        "customer_last_name": "last_name",
        "customer_gender": "gender",
        "customer_language": "language",
        "customer_email": "email",
        "customer_home_city": "home_city",
        "customer_dob": "date_of_birth",
        "customer_alias": "user_alias",
        "customer_alias_label": "alias_label",
        "pet": "set_custom_attribute.pet",
        "pet_count": "set_custom_attribute.pet_count",
        "pet_count_unset": "unset_custom_attribute.pet_count_unset",
        "pet_count_increment": "increment_custom_attribute.pet_count_increment",
        "pet_names": "set_custom_array_attribute.pet_names",
        "pet_names_append": "append_custom_array_attribute.pet_names_append",
        "pet_names_remove": "remove_custom_array_attribute.pet_names_remove",
        "facebook_user": "facebook_user",
        "number_of_friends": "friends_count",
        "list_of_likes": "likes",
        "facebook_user_properties": "facebook_user",
        "social_media_user_description": "description",
        "twitter_id": "twitter_id",
        "twitter_name": "twitter_name",
        "twitter_user_description": "description",
        "profile_image_url": "profile_image_url",
        "screen_name": "screen_name",
        "number_of_followers": "followers_count",
        "number_of_statuses": "statuses_count",
        "email_notification": "email_notification",
        "push_notification": "push_notification",
        "event_name": "event_name",
        "current_level": "event.current_level",
        "start_date": "event.start_date",
        "high_score": "event.high_score",
        "product_id": "product_id",
        "product_quantity": "quantity",
        "product_unit_price": "product_unit_price",
        "currency_code": "order_currency",
        "rewards_member": "purchase.rewards_member",
        "rewards_points_earned": "purchase.rewards_points_earned",
        "date_joined_program": "purchase.date_joined_program",
        "latitude": "location_latitude",
        "longitude": "location_longitude",
        "horizontal_accuracy": "location_horizontal_accuracy"
    },
    "commands": {
        "launch": "initialize",
        "twitter": "twitteruser",
        "facebook": "facebookuser",
        "setengagement": "emailnotification,pushnotification",
        "log_custom_event": "logcustomevent",
        "set_location": "setlastknownlocation",
        "custom_attribute": "setcustomattribute",
        "unset_custom_attribute": "unsetcustomattribute",
        "custom_array_attribute": "appendcustomarrayattribute",
        "append_custom_array_attribute": "appendcustomarrayattribute",
        "remove_custom_array_attribute": "removecustomarrayattribute",
        "increment_custom_attribute": "incrementcustomattribute",
        "log_purchase": "logpurchase",
        "user_attribute": "userattribute,useridentifier,useralias",
        "user_login": "useridentifier,useralias",
        "user_alias": "useralias"
    }
}
